ligning/__init__.py
ligning/characterization.py
ligning/monomer.py
ligning/optimization.py
ligning/polymer.py
ligning/rules.py
ligning/utils.py
ligning-0.1.1.dist-info/LICENSE
ligning-0.1.1.dist-info/METADATA
ligning-0.1.1.dist-info/WHEEL
ligning-0.1.1.dist-info/top_level.txt
ligning-0.1.1.dist-info/RECORD
