Metadata-Version: 2.1
Name: ligning
Version: 0.1.1
Summary: Accelerated Lignin Structure Generation with Graph-based Multiscale Modeling 
Home-page: https://github.com/VlachosGroup/ligningraphs
Author: Vlachos Research Group
Author-email: vlachos@udel.edu
Project-URL: Documentation, https://ligningraphs.readthedocs.io/en/latest/
Project-URL: Source, https://github.com/VlachosGroup/ligningraphs
Classifier: Programming Language :: Python :: 3
Classifier: License :: OSI Approved :: MIT License
Classifier: Operating System :: OS Independent
Classifier: Intended Audience :: Science/Research
Classifier: Topic :: Scientific/Engineering :: Chemistry
Requires-Python: >=3.7
License-File: LICENSE
Requires-Dist: matplotlib (>=3.1.1)
Requires-Dist: numpy (>=1.19.2)
Requires-Dist: scipy (>=1.3.1)
Requires-Dist: pandas (>=0.25.1)
Requires-Dist: openpyxl (>=3.0.7)
Requires-Dist: pytest (>=6.2.3)
Requires-Dist: networkx (>=2.5)
Requires-Dist: pysmiles (>=1.0.1)
Requires-Dist: rdkit-pypi (>=2021.9.2.1)
